README.md
setup.py
pkey/__init__.py
pkey.egg-info/PKG-INFO
pkey.egg-info/SOURCES.txt
pkey.egg-info/dependency_links.txt
pkey.egg-info/top_level.txt